framework/constants.py
framework/grpc/api.py
framework/grpc/clients/google/api/annotations_pb2.py
framework/grpc/clients/google/api/annotations_pb2.pyi
framework/grpc/clients/google/api/annotations_pb2_grpc.py
framework/grpc/clients/google/api/http_pb2.py
framework/grpc/clients/google/api/http_pb2.pyi
framework/grpc/clients/google/api/http_pb2_grpc.py
framework/grpc/clients/google/protobuf/timestamp_pb2.py
framework/grpc/clients/google/protobuf/timestamp_pb2.pyi
framework/grpc/clients/google/protobuf/timestamp_pb2_grpc.py
framework/grpc/clients/ozonmp/act_device_api/v1/act_device_api_pb2.py
framework/grpc/clients/ozonmp/act_device_api/v1/act_device_api_pb2.pyi
framework/grpc/clients/ozonmp/act_device_api/v1/act_device_api_pb2_grpc.py
framework/grpc/clients/protoc_gen_openapiv2/options/annotations_pb2.py
framework/grpc/clients/protoc_gen_openapiv2/options/annotations_pb2.pyi
framework/grpc/clients/protoc_gen_openapiv2/options/annotations_pb2_grpc.py
framework/grpc/clients/protoc_gen_openapiv2/options/openapiv2_pb2.py
framework/grpc/clients/protoc_gen_openapiv2/options/openapiv2_pb2.pyi
framework/grpc/clients/protoc_gen_openapiv2/options/openapiv2_pb2_grpc.py
framework/grpc/clients/validate/validate_pb2.py
framework/grpc/clients/validate/validate_pb2.pyi
framework/grpc/clients/validate/validate_pb2_grpc.py
framework/models.py
framework/rest/api.py
framework/rest/models.py
framework/sql/act_device_api_models.py
framework/sql/alchemy.py
framework/sql/client.py
framework/sql/ctx.py
framework/sql/helper.py
device_api_e2e-0.1.0.dist-info/WHEEL
device_api_e2e-0.1.0.dist-info/METADATA
device_api_e2e-0.1.0.dist-info/RECORD
