Metadata-Version: 2.1
Name: device-api-e2e
Version: 0.1.0
Summary: 
Author: aevtikheev
Author-email: aevtikheev@ozon.ru
Requires-Python: >=3.10,<4.0
Classifier: Programming Language :: Python :: 3
Classifier: Programming Language :: Python :: 3.10
Requires-Dist: PyHamcrest (>=2.0.3,<3.0.0)
Requires-Dist: SQLAlchemy (>=1.4.40,<2.0.0)
Requires-Dist: allure-pytest (>=2.9.45,<3.0.0)
Requires-Dist: allure-python-commons (>=2.9.45,<3.0.0)
Requires-Dist: grpcio-tools (>=1.47.0,<2.0.0)
Requires-Dist: psycopg2-binary (>=2.9.3,<3.0.0)
Requires-Dist: pytest (>=7.1.2,<8.0.0)
Requires-Dist: requests (>=2.28.1,<3.0.0)
